patch_manager-0.0.7.dist-info/licenses/LICENSE
patman/README.rst
patman/__init__.py
patman/__main__.py
patman/checkpatch.py
patman/cmdline.py
patman/commit.py
patman/control.py
patman/cser_helper.py
patman/cseries.py
patman/database.py
patman/func_test.py
patman/get_maintainer.py
patman/patchstream.py
patman/patchwork.py
patman/patman.rst
patman/project.py
patman/send.py
patman/series.py
patman/settings.py
patman/setup.py
patman/status.py
patman/test_checkpatch.py
patman/test_common.py
patman/test_cseries.py
patman/test_settings.py
patch_manager-0.0.7.dist-info/METADATA
patch_manager-0.0.7.dist-info/WHEEL
patch_manager-0.0.7.dist-info/entry_points.txt
patch_manager-0.0.7.dist-info/top_level.txt
patch_manager-0.0.7.dist-info/RECORD
